parasut/__init__.py
parasut/client.py
parasut/functions.py
parasut/urls.py
parasut/version.py
parasut_python-0.0.56.dist-info/LICENSE
parasut_python-0.0.56.dist-info/METADATA
parasut_python-0.0.56.dist-info/WHEEL
parasut_python-0.0.56.dist-info/top_level.txt
parasut_python-0.0.56.dist-info/RECORD
