Metadata-Version: 2.1
Name: parasut-python
Version: 0.0.56
Summary: Parasut API Python Wrapper
Home-page: https://github.com/marlonjd/parasut-python
Author: Burak Karahan
Author-email: burak.karahan@mail.ru
License: UNKNOWN
Keywords: parasut python api
Platform: UNKNOWN
Classifier: Programming Language :: Python :: 3
Classifier: License :: OSI Approved :: MIT License
Classifier: Operating System :: OS Independent
Requires-Python: >=3.6
Requires-Dist: pytest (>=6.2.1)
Requires-Dist: pytest-cov (>=2.10.1)
Requires-Dist: requests-oauthlib (>=1.3.0)
